looker_test_module
