Metadata-Version: 1.0
Name: looker-test-module
Version: 0.2
Summary: looker_test_module
Home-page: https://github.com/ripathak1988/looker-test-pip-package
Author: Rishi Pathak
Author-email: ripathak@expedia.com
License: UNKNOWN
Platform: UNKNOWN
